kagura/__init__.py
kagura/exceptions.py
kagura/version.py
kagura/agents/__init__.py
kagura/agents/chatbot.py
kagura/agents/code_execution.py
kagura/agents/summarizer.py
kagura/agents/translate_func.py
kagura/agents/translator.py
kagura/api/__init__.py
kagura/api/auth.py
kagura/api/dependencies.py
kagura/api/models.py
kagura/api/server.py
kagura/api/routes/__init__.py
kagura/api/routes/graph.py
kagura/api/routes/mcp_transport.py
kagura/api/routes/memory.py
kagura/api/routes/models.py
kagura/api/routes/search.py
kagura/api/routes/system.py
kagura/auth/__init__.py
kagura/auth/config.py
kagura/auth/exceptions.py
kagura/auth/oauth2.py
kagura/builder/__init__.py
kagura/builder/agent_builder.py
kagura/builder/config.py
kagura/builtin/__init__.py
kagura/builtin/file.py
kagura/builtin/git.py
kagura/builtin/github_agent.py
kagura/builtin/shell.py
kagura/cli/__init__.py
kagura/cli/api_cli.py
kagura/cli/auth_cli.py
kagura/cli/config_cli.py
kagura/cli/doctor.py
kagura/cli/init.py
kagura/cli/lazy.py
kagura/cli/main.py
kagura/cli/monitor.py
kagura/cli/telemetry_cli.py
kagura/cli/coding/__init__.py
kagura/cli/coding/decisions.py
kagura/cli/coding/errors.py
kagura/cli/coding/sessions.py
kagura/cli/coding/utils.py
kagura/cli/mcp/__init__.py
kagura/cli/mcp/config.py
kagura/cli/mcp/core.py
kagura/cli/mcp/monitor.py
kagura/cli/mcp/telemetry.py
kagura/cli/mcp/tools.py
kagura/cli/memory/__init__.py
kagura/cli/memory/diagnostics.py
kagura/cli/memory/operations.py
kagura/cli/memory/query.py
kagura/cli/memory/setup.py
kagura/cli/utils/__init__.py
kagura/commands/__init__.py
kagura/commands/command.py
kagura/commands/executor.py
kagura/commands/hook_decorators.py
kagura/commands/hooks.py
kagura/commands/loader.py
kagura/config/__init__.py
kagura/config/env.py
kagura/config/manager.py
kagura/config/memory_config.py
kagura/config/models.py
kagura/config/paths.py
kagura/config/project.py
kagura/core/__init__.py
kagura/core/cache.py
kagura/core/decorators.py
kagura/core/executor.py
kagura_ai-4.3.1.dist-info/LICENSE
kagura_ai-4.3.1.dist-info/METADATA
kagura_ai-4.3.1.dist-info/WHEEL
kagura_ai-4.3.1.dist-info/entry_points.txt
kagura_ai-4.3.1.dist-info/top_level.txt
kagura_ai-4.3.1.dist-info/RECORD
