Metadata-Version: 2.1
Name: kagura-ai
Version: 4.3.1
Summary: Universal AI Memory Platform - MCP-native context management for all AI agents
Author-email: JFK <fumikazu.kiyota@gmail.com>
Keywords: ai,memory,mcp,context,knowledge-graph,rag,llm,agents,claude,chatgpt,gemini,vector-db,local-first,privacy,pydantic,async
Classifier: Development Status :: 5 - Production/Stable
Classifier: Intended Audience :: Developers
Classifier: License :: OSI Approved :: Apache Software License
Classifier: Programming Language :: Python :: 3
Classifier: Programming Language :: Python :: 3.11
Classifier: Programming Language :: Python :: 3.12
Classifier: Programming Language :: Python :: 3.13
Classifier: Topic :: Software Development :: Libraries :: Python Modules
Classifier: Topic :: Scientific/Engineering :: Artificial Intelligence
Classifier: Typing :: Typed
Requires-Python: >=3.11
License-File: LICENSE
Requires-Dist: pydantic>=2.10
Requires-Dist: click>=8.1
Requires-Dist: openai>=1.0.0
Requires-Dist: litellm>=1.0
Requires-Dist: jinja2>=3.1
Requires-Dist: rich>=13.0
Requires-Dist: python-dotenv>=1.0
Requires-Dist: prompt-toolkit>=3.0.52
Requires-Dist: pygments>=2.19.2
Requires-Dist: python-frontmatter>=1.0.0
Requires-Dist: arxiv>=2.2.0
Requires-Dist: brave-search-python-client>=0.4.0
Requires-Dist: psutil>=5.9.0
Provides-Extra: ai
Requires-Dist: chromadb>=0.4.0; extra == "ai"
Requires-Dist: torch<2.3,>=2.0.0; extra == "ai"
Requires-Dist: torchvision<0.18,>=0.15.0; extra == "ai"
Requires-Dist: sentence-transformers<5.2,>=2.2.0; extra == "ai"
Requires-Dist: numpy<2.0,>=1.24.0; extra == "ai"
Requires-Dist: rank-bm25>=0.2.2; extra == "ai"
Requires-Dist: semantic-router>=0.1.11; extra == "ai"
Requires-Dist: tiktoken>=0.7.0; extra == "ai"
Requires-Dist: langchain-text-splitters>=0.0.1; extra == "ai"
Provides-Extra: all
Requires-Dist: kagura-ai[full]; extra == "all"
Requires-Dist: kagura-ai[dev]; extra == "all"
Requires-Dist: kagura-ai[docs]; extra == "all"
Provides-Extra: api
Requires-Dist: fastapi>=0.115.0; extra == "api"
Requires-Dist: uvicorn[standard]>=0.32.0; extra == "api"
Requires-Dist: psycopg2-binary>=2.9.9; extra == "api"
Requires-Dist: asyncpg>=0.29.0; extra == "api"
Requires-Dist: redis>=5.0.0; extra == "api"
Requires-Dist: python-multipart>=0.0.9; extra == "api"
Provides-Extra: auth
Requires-Dist: google-auth>=2.25.0; extra == "auth"
Requires-Dist: google-auth-oauthlib>=1.2.0; extra == "auth"
Requires-Dist: google-auth-httplib2>=0.2.0; extra == "auth"
Requires-Dist: cryptography>=41.0.0; extra == "auth"
Provides-Extra: dev
Requires-Dist: pytest>=8.3; extra == "dev"
Requires-Dist: pytest-asyncio>=0.25; extra == "dev"
Requires-Dist: pytest-cov>=6.0; extra == "dev"
Requires-Dist: pytest-timeout>=2.3; extra == "dev"
Requires-Dist: pytest-xdist>=3.5; extra == "dev"
Requires-Dist: langdetect>=1.0.9; extra == "dev"
Requires-Dist: ruff>=0.8; extra == "dev"
Requires-Dist: pyright>=1.1.406; extra == "dev"
Provides-Extra: docs
Requires-Dist: mkdocs>=1.6; extra == "docs"
Requires-Dist: mkdocs-material>=9.5; extra == "docs"
Requires-Dist: mkdocs-static-i18n>=1.2.0; extra == "docs"
Requires-Dist: pymdown-extensions>=10.0; extra == "docs"
Provides-Extra: full
Requires-Dist: kagura-ai[ai]; extra == "full"
Requires-Dist: kagura-ai[api]; extra == "full"
Requires-Dist: kagura-ai[graph]; extra == "full"
Requires-Dist: kagura-ai[web]; extra == "full"
Requires-Dist: kagura-ai[auth]; extra == "full"
Requires-Dist: kagura-ai[mcp]; extra == "full"
Provides-Extra: graph
Requires-Dist: networkx>=3.0; extra == "graph"
Provides-Extra: mcp
Requires-Dist: mcp>=1.0.0; extra == "mcp"
Requires-Dist: jsonschema>=4.20.0; extra == "mcp"
Provides-Extra: web
Requires-Dist: google-generativeai>=0.8.0; extra == "web"
Requires-Dist: pillow>=10.0.0; extra == "web"
Requires-Dist: proto-plus<2.0.0dev; extra == "web"
Requires-Dist: protobuf<6.0.0,>=4.25.0; extra == "web"
Requires-Dist: httpx>=0.25.0; extra == "web"
Requires-Dist: beautifulsoup4>=4.12.0; extra == "web"
Requires-Dist: youtube-transcript-api>=0.6.0; extra == "web"
Requires-Dist: yt-dlp>=2023.0.0; extra == "web"
